README.md
setup.cfg
setup.py
sorting_array/__init__.py
sorting_array/__main__.py
sorting_array/sorting.py
sorting_array.egg-info/PKG-INFO
sorting_array.egg-info/SOURCES.txt
sorting_array.egg-info/dependency_links.txt
sorting_array.egg-info/top_level.txt