Metadata-Version: 2.1
Name: sorting-array
Version: 0.1
Summary: Sorting an array
Author: Ilya Romitsyn
Author-email: ilya.romitsyn@mail.ru
